{"chunk_definitions":[{"row":14,"row_count":1,"visible":true,"expansion_state":0,"options":{"engine":"r","label":"setup4","include":false,"dev":"png"},"document_id":"8D93338C","chunk_id":"csetup_chunk","chunk_label":"setup4"},{"row":31,"row_count":1,"visible":true,"expansion_state":0,"options":{"engine":"r","include":false,"label":"unnamed-chunk-1","dev":"png"},"document_id":"8D93338C","chunk_id":"ch49n6a0zqe63","chunk_label":"unnamed-chunk-1"},{"row":48,"row_count":1,"visible":true,"expansion_state":0,"options":{"engine":"r","label":"chargementg","echo":false,"dev":"png"},"document_id":"8D93338C","chunk_id":"cyactyik6qia0","chunk_label":"chargementg"},{"row":70,"row_count":1,"visible":true,"expansion_state":0,"options":{"engine":"r","label":"prtyg","echo":false,"dev":"png"},"document_id":"8D93338C","chunk_id":"cbzwhc9vfpgsd","chunk_label":"prtyg"},{"row":95,"row_count":1,"visible":true,"expansion_state":0,"options":{"engine":"r","label":"metyh","echo":false,"cache":false,"dev":"png"},"document_id":"B2AC6511","chunk_id":"c479l7ecyf5m7","chunk_label":"metyh"},{"row":192,"row_count":1,"visible":true,"expansion_state":0,"options":{"engine":"r","label":"maptfo","echo":false,"dev":"png"},"document_id":"B2AC6511","chunk_id":"cv6iyaz7p6ehn","chunk_label":"maptfo"},{"row":307,"row_count":1,"visible":true,"expansion_state":0,"options":{"engine":"r","label":"mefo","echo":false,"cache":false,"dev":"png"},"document_id":"B2AC6511","chunk_id":"cu0ykis4ftj9q","chunk_label":"mefo"},{"row":403,"row_count":1,"visible":true,"expansion_state":0,"options":{"engine":"r","label":"maptao","echo":false,"fig.width":5,"fig.height":4,"dev":"png"},"document_id":"179C3465","chunk_id":"c8f28wyiea07u","chunk_label":"maptao"},{"row":548,"row_count":1,"visible":true,"expansion_state":0,"options":{"engine":"r","label":"maptao","echo":false,"fig.width":5,"fig.height":4,"dev":"png"},"document_id":"B2AC6511","chunk_id":"cap3z3r5o59au","chunk_label":"maptao"},{"row":594,"row_count":1,"visible":true,"expansion_state":0,"options":{"engine":"r","label":"mapeao","echo":false,"dev":"png"},"document_id":"761E4FD5","chunk_id":"ckmppjwquubum","chunk_label":"mapeao"},{"row":642,"row_count":1,"visible":true,"expansion_state":0,"options":{"engine":"r","label":"aoao","echo":false,"dev":"png"},"document_id":"761E4FD5","chunk_id":"cqnmpo3fppl06","chunk_label":"aoao"},{"row":680,"row_count":1,"visible":true,"expansion_state":0,"options":{"engine":"r","label":"pfrtygs","echo":false,"message":false,"dev":"png"},"document_id":"179C3465","chunk_id":"ck1gld63b08wu","chunk_label":"pfrtygs"},{"row":710,"row_count":1,"visible":true,"expansion_state":0,"options":{"engine":"r","label":"prtygsrd","echo":false,"message":false,"dev":"png"},"document_id":"761E4FD5","chunk_id":"c7trnjvjac0k0","chunk_label":"prtygsrd"},{"row":743,"row_count":1,"visible":true,"expansion_state":0,"options":{"engine":"r","label":"prtygessf","echo":false,"message":false,"dev":"png"},"document_id":"179C3465","chunk_id":"clgh3ci4xp71n","chunk_label":"prtygessf"},{"row":774,"row_count":1,"visible":true,"expansion_state":0,"options":{"engine":"r","label":"vhe","echo":false,"message":false,"dev":"png"},"document_id":"761E4FD5","chunk_id":"c5ex0te2n2y5p","chunk_label":"vhe"},{"row":808,"row_count":1,"visible":true,"expansion_state":0,"options":{"engine":"r","label":"prteygs","echo":false,"message":false,"dev":"png"},"document_id":"761E4FD5","chunk_id":"cz2gdvzblx63h","chunk_label":"prteygs"},{"row":842,"row_count":1,"visible":true,"expansion_state":0,"options":{"engine":"r","label":"prteygs","echo":false,"message":false,"dev":"png"},"document_id":"B2AC6511","chunk_id":"crcz1r7fcege0","chunk_label":"prteygs"},{"row":872,"row_count":1,"visible":true,"expansion_state":0,"options":{"engine":"r","label":"prtygsd","echo":false,"dev":"png"},"document_id":"761E4FD5","chunk_id":"clhgr926au1g6","chunk_label":"pertygsd"},{"row":905,"row_count":1,"visible":true,"expansion_state":0,"options":{"engine":"r","label":"prtygssf","echo":false,"dev":"png"},"document_id":"761E4FD5","chunk_id":"c6lpzraea7kxe","chunk_label":"eprtygssf"},{"row":936,"row_count":1,"visible":true,"expansion_state":0,"options":{"engine":"r","label":"vh","echo":false,"dev":"png"},"document_id":"761E4FD5","chunk_id":"c4iogyg1rfa8h","chunk_label":"zvh"},{"row":970,"row_count":1,"visible":true,"expansion_state":0,"options":{"engine":"r","label":"prtyzgs","echo":false,"message":false,"dev":"png"},"document_id":"761E4FD5","chunk_id":"chsrqzwvmqgyk","chunk_label":"prtyzgs"},{"row":1002,"row_count":1,"visible":true,"expansion_state":0,"options":{"engine":"r","label":"prtygs","echo":false,"dev":"png"},"document_id":"761E4FD5","chunk_id":"cahvaenw4c4s6","chunk_label":"prtzygs"},{"row":1033,"row_count":1,"visible":true,"expansion_state":0,"options":{"engine":"r","label":"prtygs","echo":false,"dev":"png"},"document_id":"761E4FD5","chunk_id":"cwuxd38hgdar5","chunk_label":"pzrtygs"},{"row":1064,"row_count":1,"visible":true,"expansion_state":0,"options":{"engine":"r","label":"prtygs","echo":false,"dev":"png"},"document_id":"761E4FD5","chunk_id":"cxqetnj337g79","chunk_label":"zprtygs"},{"row":1079,"row_count":1,"visible":true,"expansion_state":0,"options":{"engine":"r","label":"prtygsbm","echo":false,"dev":"png"},"document_id":"8D93338C","chunk_id":"ct98nn5ccm4kz","chunk_label":"prtyzgsbm"},{"row":1104,"row_count":1,"visible":true,"expansion_state":0,"options":{"engine":"r","label":"prtygsbte","echo":false,"dev":"png"},"document_id":"179C3465","chunk_id":"cqiu3kvia38e3","chunk_label":"prztygsbte"},{"row":1127,"row_count":1,"visible":true,"expansion_state":0,"options":{"engine":"r","label":"prtygsbte","echo":false,"dev":"png"},"document_id":"761E4FD5","chunk_id":"cxw2oj8jnkm8i","chunk_label":"pzrtygsbte"},{"row":1149,"row_count":1,"visible":true,"expansion_state":0,"options":{"engine":"r","label":"prtygsbte","echo":false,"dev":"png"},"document_id":"761E4FD5","chunk_id":"ciew4d41ut89b","chunk_label":"zprtygsbte"},{"row":1171,"row_count":1,"visible":true,"expansion_state":0,"options":{"engine":"r","label":"prtygsbte","echo":false,"dev":"png"},"document_id":"761E4FD5","chunk_id":"catd1ac9ggppa","chunk_label":"prtygsbtea"},{"row":1202,"row_count":1,"visible":true,"expansion_state":0,"options":{"engine":"r","label":"prtygsbte","echo":false,"dev":"png"},"document_id":"761E4FD5","chunk_id":"ccbbk9elhdtrt","chunk_label":"prtygsbtae"},{"row":1225,"row_count":1,"visible":true,"expansion_state":0,"options":{"engine":"r","label":"prtygsbte","echo":false,"dev":"png"},"document_id":"761E4FD5","chunk_id":"ca0dh857fcsbt","chunk_label":"prtygsbate"},{"row":1249,"row_count":1,"visible":true,"expansion_state":0,"options":{"engine":"r","label":"prtygsbte","echo":false,"dev":"png"},"document_id":"761E4FD5","chunk_id":"ckjpbb2wdny1p","chunk_label":"prtygsabte"},{"row":1275,"row_count":1,"visible":true,"expansion_state":0,"options":{"engine":"r","label":"prtygsbte","echo":false,"dev":"png"},"document_id":"761E4FD5","chunk_id":"crq5hrnn3kbse","chunk_label":"prtygasbte"},{"row":1303,"row_count":1,"visible":true,"expansion_state":0,"options":{"engine":"r","label":"prtygsbte","echo":false,"dev":"png"},"document_id":"761E4FD5","chunk_id":"crkrhjncpv70r","chunk_label":"prtyagsbte"},{"row":1327,"row_count":1,"visible":true,"expansion_state":0,"options":{"engine":"r","label":"prtygsbte","echo":false,"dev":"png"},"document_id":"761E4FD5","chunk_id":"cs0in6g99gevs","chunk_label":"prtaygsbte"},{"row":1350,"row_count":1,"visible":true,"expansion_state":0,"options":{"engine":"r","label":"prtygsbte","echo":false,"dev":"png"},"document_id":"761E4FD5","chunk_id":"cd2kgfon14xmn","chunk_label":"partygsbte"},{"row":1374,"row_count":1,"visible":true,"expansion_state":0,"options":{"engine":"r","label":"prtygsbte","echo":false,"dev":"png"},"document_id":"761E4FD5","chunk_id":"c2f91dxby2196","chunk_label":"aprtygsbte"}],"doc_write_time":1711551221,"chunk_rendered_width":700}